Workbook

Sheet Market Inputs
A1: PBSA ↔ PRS Anchoring Model — Market Inputs
A2: Munich · Innsbruck · Passau | March 2026
A4: A. CITY-LEVEL DEMOGRAPHICS & MARKET CONTEXT
A5: Metric | B5: Munich | C5: Innsbruck | D5: Passau | E5: Unit | F5: Source
A6: Total Student Population | B6: 130000 | C6: 35000 | D6: 10568 | E6: students | F6: DACH Market Data 2025; Uni Passau Dec 2025
A7: No. of Universities / HEIs | B7: 16 | C7: 5 | D7: 1 | E7: institutions | F7: Universities dataset
A8: International Students | B8: 37627 | C8: 15272 | D8: 1916 | E8: students | F8: University enrollment data
A9: International Student % | B9: =B8/B6 -> 0.28943846 | C9: =C8/C6 -> 0.43634286 | D9: =D8/D6 -> 0.18130204 | E9: % | F9: Formula
A10: Provision Rate (PBSA Beds / Students) | B10: =B11/B6 -> 0.092307692 | C10: =C11/C6 -> 0.085714286 | D10: =D11/D6 -> 0.11355034 | E10: % | F10: Formula
A11: PBSA Beds (approx.) | B11: 12000 | C11: 3000 | D11: 1200 | E11: beds | F11: DACH Market Data; residences inventory
A12: City Population | B12: 1512000 | C12: 131000 | D12: 54000 | E12: residents | F12: Eurostat / municipal stats
A13: Median Household Income | B13: 52000 | C13: 38000 | D13: 32000 | E13: €/year | F13: Destatis / Statistik Austria (est.)
A14: GDP per Capita | B14: 79000 | C14: 55000 | D14: 35000 | E14: €/year | F14: Eurostat NUTS-3 (est.)
A15: PRS Avg Rent (€/sqm/mo) | B15: 23 | C15: 21 | D15: 10 | E15: €/sqm | F15: ImmoScout24 / Wohnungsboerse Q1 2026
A16: PRS Rent Growth (YoY) | B16: 0.034 | C16: 0.04 | D16: 0.03 | E16: % | F16: DACH Market Data 2025
A17: Avg PBSA Rent (€/mo) | B17: 1374 | C17: 520 | D17: 350 | E17: €/mo | F17: DACH Market Data 2025
A18: Premium PBSA Rent (€/mo) | B18: 1919 | C18: 700 | D18: 550 | E18: €/mo | F18: THE FIZZ / DACH Data (top-tier)
A19: Studentenwerk Benchmark (€/mo) | B19: 401 | C19: 350 | D19: 280 | E19: €/mo | F19: Studierendenwerk / OeAD benchmarks
A20: PBSA Occupancy Rate | B20: 0.96 | C20: 0.93 | D20: 0.95 | E20: % | F20: DACH Market Data 2025
A21: PBSA Rent Growth (YoY) | B21: 0.048 | C21: 0.05 | D21: 0.035 | E21: % | F21: DACH Market Data 2025
A23: B. UNIVERSITY PRESTIGE INDICATORS
A24: University | B24: City | C24: QS World Rank (2025) | D24: THE Rank (2025) | E24: Prestige Score (1-10) | F24: Intl Students | G24: Notes
A25: LMU Munich | B25: Munich | C25: 59 | D25: 38 | E25: 9 | F25: 11658 | G25: Top-ranked German university
A26: TU Munich (TUM) | B26: Munich | C26: 28 | D26: 30 | E26: 10 | F26: 23379 | G26: 45% international; STEM powerhouse
A27: HM Munich (UAS) | B27: Munich | C27: N/A | D27: N/A | E27: 5 | F27: 2400 | G27: Applied sciences
A28: Universität Innsbruck | B28: Innsbruck | C28: 266 | D28: 301-350 | E28: 7 | F28: 13972 | G28: 49.9% international; strong in STEM & humanities
A29: MedUni Innsbruck | B29: Innsbruck | C29: N/A | D29: N/A | E29: 7 | F29: 1300 | G29: Medical university
A30: MCI Innsbruck | B30: Innsbruck | C30: N/A | D30: N/A | E30: 5 | F30: ~1,500 | G30: 63 nations represented
A31: Universität Passau | B31: Passau | C31: 601-650 | D31: 351-400 | E31: 5 | F31: 1916 | G31: 18.1% international; strong in law, business

Sheet PRS Benchmark
A1: PRS (Private Rented Sector) Benchmark by City
A3: A. PRS RENT SUMMARY (€/sqm/month — New Leases)
A4: Metric | B4: Munich | C4: Innsbruck | D4: Passau | E4: Unit
A5: City Centre | B5: 27 | C5: 25 | D5: 12 | E5: €/sqm/mo
A6: Outside Centre | B6: 18 | C6: 18 | D6: 8.5 | E6: €/sqm/mo
A7: City Average (New Leases) | B7: =AVERAGE(B5,B6) -> 22.5 | C7: =AVERAGE(C5,C6) -> 21.5 | D7: =AVERAGE(D5,D6) -> 10.25 | E7: €/sqm/mo
A8: Existing Contracts (Mietspiegel) | B8: 15 | C8: 13 | D8: 7.5 | E8: €/sqm/mo
A10: B. PRS MONTHLY RENT BY UNIT TYPE (Formula: Avg €/sqm × Size)
A11: Unit Type | B11: Size (sqm) | C11: Munich (€/mo) | D11: Innsbruck (€/mo) | E11: Passau (€/mo)
A12: Micro Studio | B12: 18 | C12: ='PRS Benchmark'!B7*B12 -> 405 | D12: ='PRS Benchmark'!C7*B12 -> 387 | E12: ='PRS Benchmark'!D7*B12 -> 184.5
A13: Classic Studio | B13: 22 | C13: ='PRS Benchmark'!B7*B13 -> 495 | D13: ='PRS Benchmark'!C7*B13 -> 473 | E13: ='PRS Benchmark'!D7*B13 -> 225.5
A14: Premium Studio | B14: 28 | C14: ='PRS Benchmark'!B7*B14 -> 630 | D14: ='PRS Benchmark'!C7*B14 -> 602 | E14: ='PRS Benchmark'!D7*B14 -> 287
A15: 1-Bed Apartment | B15: 35 | C15: ='PRS Benchmark'!B7*B15 -> 787.5 | D15: ='PRS Benchmark'!C7*B15 -> 752.5 | E15: ='PRS Benchmark'!D7*B15 -> 358.75
A16: 1-Bed City Centre | B16: 45 | C16: ='PRS Benchmark'!B7*B16 -> 1012.5 | D16: ='PRS Benchmark'!C7*B16 -> 967.5 | E16: ='PRS Benchmark'!D7*B16 -> 461.25
A18: C. PRS FROM SCRAPED LISTINGS (Innsbruck — Cleaned Dataset, n=170)
A19: Statistic | B19: Price (€/mo) | C19: Size (m²) | D19: €/m²
A20: Mean | B20: 1381 | C20: 52 | D20: 29.5
A21: Median | B21: 1380 | C21: 49 | D21: 27.5
A22: 25th Percentile | B22: 900 | C22: 32 | D22: 23.1
A23: 75th Percentile | B23: 1663 | C23: 70 | D23: 32.8
A24: 90th Percentile (Top Tier PRS) | B24: 2299 | C24: 99 | D24: 42.1
A25: Count | B25: 170 | C25: 163 | D25: 163

Sheet PBSA Comparables
A1: PBSA Comparables — Operational Inventory with Pricing
A3: A. MUNICH — PREMIUM PBSA OPERATORS
A4: Operator | B4: Segment | C4: Room Type | D4: Size (sqm) | E4: All-In Rent (€/mo) | F4: Eff. €/sqm/mo | G4: Includes | H4: Proximity to Uni
A5: THE FIZZ Munich | B5: Premium | C5: Single Studio | D5: 22 | E5: 1424 | F5: =E5/D5 -> 64.727273 | G5: Utils, WiFi, furniture | H5: 10 min to LMU/TUM
A6: THE FIZZ Munich | B6: Premium | C6: Flex Apartment | D6: 40 | E6: 1919 | F6: =E6/D6 -> 47.975 | G6: Utils, WiFi, furniture | H6: 10 min to LMU/TUM
A7: TheBase Munich | B7: Ultra-Premium | C7: Studio | D7: 25 | E7: 1299 | F7: =E7/D7 -> 51.96 | G7: All-in; co-living | H7: Central
A8: Revo Munich | B8: Ultra-Premium | C8: Studio | D8: 28 | E8: 1800 | F8: =E8/D8 -> 64.285714 | G8: All-in; premium co-living | H8: Central
A9: THE HOUSE OF CO | B9: Premium | C9: Co-Living Studio | D9: 20 | E9: 900 | F9: =E9/D9 -> 45 | G9: Furnished, community | H9: Central
A10: Nido Alp Studios | B10: Premium | C10: Studio | D10: 22 | E10: 899 | F10: =E10/D10 -> 40.863636 | G10: Furnished, all-in | H10: Near TUM
A11: Deutsche Burse | B11: Mid-Range | C11: Studio | D11: 20 | E11: 820 | F11: =E11/D11 -> 41 | G11: Furnished | H11: Schwabing
A12: Campus Viva Munich V | B12: Mid-Range | C12: Studio | D12: 22 | E12: 890 | F12: =E12/D12 -> 40.454545 | G12: Net + utils | H12: South Munich
A13: Studio M2 | B13: Budget-Premium | C13: Studio | D13: 21 | E13: 560 | F13: =E13/D13 -> 26.666667 | G13: Kaltmiete + NK | H13: Near universities
A14: YOUNIQ Munich | B14: Budget-Premium | C14: Micro Studio | D14: 22 | E14: 704 | F14: =E14/D14 -> 32 | G14: All-in | H14: Near universities
A15: Uni Apart Munich | B15: Mid-Range | C15: Studio | D15: 25 | E15: 750 | F15: =E15/D15 -> 30 | G15: Furnished, some utils | H15: Multiple locations
A16: Staytoo Munich | B16: Mid-Range | C16: Studio | D16: 22 | E16: 925 | F16: =E16/D16 -> 42.045455 | G16: All-in | H16: Central
A17: The Stay Residence | B17: Mid-Range | C17: Studio | D17: 24 | E17: 800 | F17: =E17/D17 -> 33.333333 | G17: Furnished | H17: Near centre
A19: SUMMARY
A20: Avg Premium PBSA (€/mo) | E20: =AVERAGEIFS(E5:E17,B5:B17,"Premium") -> 1285.5 | F20: =AVERAGEIFS(F5:F17,B5:B17,"Premium") -> 49.641477
A21: Avg Ultra-Premium PBSA (€/mo) | E21: =AVERAGEIFS(E5:E17,B5:B17,"Ultra-Premium") -> 1549.5 | F21: =AVERAGEIFS(F5:F17,B5:B17,"Ultra-Premium") -> 58.122857
A22: Avg Mid-Range PBSA (€/mo) | E22: =AVERAGEIFS(E5:E17,B5:B17,"Mid-Range") -> 837 | F22: =AVERAGEIFS(F5:F17,B5:B17,"Mid-Range") -> 37.366667
A23: Avg Budget-Premium PBSA (€/mo) | E23: =AVERAGEIFS(E5:E17,B5:B17,"Budget-Premium") -> 632 | F23: =AVERAGEIFS(F5:F17,B5:B17,"Budget-Premium") -> 29.333333
A24: Overall Avg PBSA (€/mo) | E24: =AVERAGE(E5:E17) -> 1053.0769 | F24: =AVERAGE(F5:F17) -> 43.100894
A26: B. STUDENTENWERK / PUBLIC HOUSING BENCHMARKS
A27: City | B27: Operator | C27: Avg Low (€/mo) | D27: Avg High (€/mo) | E27: Midpoint (€/mo) | F27: Est. Size (sqm) | G27: Eff. €/sqm/mo
A28: Munich | B28: Studierendenwerk München | C28: 275 | D28: 430 | E28: =AVERAGE(C28,D28) -> 352.5 | F28: 18 | G28: =E28/F28 -> 19.583333
A29: Innsbruck | B29: OeAD / Wihast / Heim operators | C29: 298 | D29: 450 | E29: =AVERAGE(C29,D29) -> 374 | F29: 16 | G29: =E29/F29 -> 23.375
A30: Passau | B30: Studierendenwerk Niederbayern | C30: 250 | D30: 400 | E30: =AVERAGE(C30,D30) -> 325 | F30: 16 | G30: =E30/F30 -> 20.3125

Sheet Pricing Model
A1: Premium PBSA Pricing Model — Anchored to PRS
A2: Compares Top-Tier PBSA vs PRS vs Studentenwerk vs Average PBSA
A4: A. DERIVED MULTIPLIERS FROM MUNICH BENCHMARK
A5: Comparison | B5: PBSA Rent (€/mo) | C5: PRS Equiv (€/mo) | D5: Premium Multiplier | E5: Premium %
A6: Ultra-Premium PBSA vs PRS (Munich) | B6: =AVERAGE('PBSA Comparables'!E8,'PBSA Comparables'!E9) -> 1350 | C6: ='PRS Benchmark'!C13 -> 495 | D6: =B6/C6 -> 2.7272727 | E6: =D6-1 -> 1.7272727
A7: Premium PBSA vs PRS (Munich) | B7: ='PBSA Comparables'!E20 -> 1285.5 | C7: ='PRS Benchmark'!C13 -> 495 | D7: =B7/C7 -> 2.5969697 | E7: =D7-1 -> 1.5969697
A8: Mid-Range PBSA vs PRS (Munich) | B8: ='PBSA Comparables'!E22 -> 837 | C8: ='PRS Benchmark'!C13 -> 495 | D8: =B8/C8 -> 1.6909091 | E8: =D8-1 -> 0.69090909
A9: PBSA vs Studentenwerk (Munich) | B9: ='PBSA Comparables'!E24 -> 1053.0769 | C9: ='PBSA Comparables'!E28 -> 352.5 | D9: =B9/C9 -> 2.9874523 | E9: =D9-1 -> 1.9874523
A11: B. MODELLED PREMIUM PBSA PRICING BY CITY & UNIT TYPE
A12: Applies Munich-derived multiplier to local PRS rents
A13: City | B13: Unit Type | C13: Size (sqm) | D13: Local PRS €/sqm | E13: Premium Multiplier | F13: Modelled €/sqm/mo | G13: Modelled All-In (€/mo) | H13: vs Studentenwerk Premium | I13: vs Avg PBSA Premium
A14: Munich | B14: Micro Studio | C14: 18 | D14: ='Market Inputs'!B15 -> 23 | E14: =$D$7 -> 2.5969697 | F14: =D14*E14 -> 59.730303 | G14: =F14*C14 -> 1075.1455 | H14: =G14/'PBSA Comparables'!E28-1 -> 2.050058 | I14: =G14/'PBSA Comparables'!E24-1 -> 0.020956239
A15: Munich | B15: Classic Studio | C15: 22 | D15: ='Market Inputs'!B15 -> 23 | E15: =$D$7 -> 2.5969697 | F15: =D15*E15 -> 59.730303 | G15: =F15*C15 -> 1314.0667 | H15: =G15/'PBSA Comparables'!E28-1 -> 2.7278487 | I15: =G15/'PBSA Comparables'!E24-1 -> 0.2478354
A16: Munich | B16: Premium Studio | C16: 28 | D16: ='Market Inputs'!B15 -> 23 | E16: =$D$7 -> 2.5969697 | F16: =D16*E16 -> 59.730303 | G16: =F16*C16 -> 1672.4485 | H16: =G16/'PBSA Comparables'!E28-1 -> 3.7445347 | I16: =G16/'PBSA Comparables'!E24-1 -> 0.58815415
A17: Munich | B17: 1-Bed Apartment | C17: 35 | D17: ='Market Inputs'!B15 -> 23 | E17: =$D$7 -> 2.5969697 | F17: =D17*E17 -> 59.730303 | G17: =F17*C17 -> 2090.5606 | H17: =G17/'PBSA Comparables'!E28-1 -> 4.9306684 | I17: =G17/'PBSA Comparables'!E24-1 -> 0.98519269
A19: Innsbruck | B19: Micro Studio | C19: 18 | D19: ='Market Inputs'!C15 -> 21 | E19: =$D$7 -> 2.5969697 | F19: =D19*E19 -> 54.536364 | G19: =F19*C19 -> 981.65455 | H19: =G19/'PBSA Comparables'!E29-1 -> 1.6247448 | I19: =G19/'PBSA Comparables'!E24-1 -> -0.067822565
A20: Innsbruck | B20: Classic Studio | C20: 22 | D20: ='Market Inputs'!C15 -> 21 | E20: =$D$7 -> 2.5969697 | F20: =D20*E20 -> 54.536364 | G20: =F20*C20 -> 1199.8 | H20: =G20/'PBSA Comparables'!E29-1 -> 2.2080214 | I20: =G20/'PBSA Comparables'!E24-1 -> 0.13932798
A21: Innsbruck | B21: Premium Studio | C21: 28 | D21: ='Market Inputs'!C15 -> 21 | E21: =$D$7 -> 2.5969697 | F21: =D21*E21 -> 54.536364 | G21: =F21*C21 -> 1527.0182 | H21: =G21/'PBSA Comparables'!E29-1 -> 3.0829363 | I21: =G21/'PBSA Comparables'!E24-1 -> 0.45005379
A22: Innsbruck | B22: 1-Bed Apartment | C22: 35 | D22: ='Market Inputs'!C15 -> 21 | E22: =$D$7 -> 2.5969697 | F22: =D22*E22 -> 54.536364 | G22: =F22*C22 -> 1908.7727 | H22: =G22/'PBSA Comparables'!E29-1 -> 4.1036704 | I22: =G22/'PBSA Comparables'!E24-1 -> 0.81256724
A24: Passau | B24: Micro Studio | C24: 18 | D24: ='Market Inputs'!D15 -> 10 | E24: =$D$7 -> 2.5969697 | F24: =D24*E24 -> 25.969697 | G24: =F24*C24 -> 467.45455 | H24: =G24/'PBSA Comparables'!E30-1 -> 0.43832168 | I24: =G24/'PBSA Comparables'!E24-1 -> -0.55610598
A25: Passau | B25: Classic Studio | C25: 22 | D25: ='Market Inputs'!D15 -> 10 | E25: =$D$7 -> 2.5969697 | F25: =D25*E25 -> 25.969697 | G25: =F25*C25 -> 571.33333 | H25: =G25/'PBSA Comparables'!E30-1 -> 0.75794872 | I25: =G25/'PBSA Comparables'!E24-1 -> -0.45746287
A26: Passau | B26: Premium Studio | C26: 28 | D26: ='Market Inputs'!D15 -> 10 | E26: =$D$7 -> 2.5969697 | F26: =D26*E26 -> 25.969697 | G26: =F26*C26 -> 727.15152 | H26: =G26/'PBSA Comparables'!E30-1 -> 1.2373893 | I26: =G26/'PBSA Comparables'!E24-1 -> -0.3094982
A27: Passau | B27: 1-Bed Apartment | C27: 35 | D27: ='Market Inputs'!D15 -> 10 | E27: =$D$7 -> 2.5969697 | F27: =D27*E27 -> 25.969697 | G27: =F27*C27 -> 908.93939 | H27: =G27/'PBSA Comparables'!E30-1 -> 1.7967366 | I27: =G27/'PBSA Comparables'!E24-1 -> -0.13687274
A30: C. SIDE-BY-SIDE: PREMIUM PBSA vs PRS vs STUDENTENWERK vs AVG PBSA
A31: City | B31: Studentenwerk (€/mo) | C31: Avg PRS Studio 22sqm (€/mo) | D31: Avg PBSA (€/mo) | E31: Premium PBSA (€/mo) | F31: Top-Tier / Ultra (€/mo) | G31: Premium / Studentenwerk | H31: Premium / PRS | I31: Premium / Avg PBSA
A32: Munich | B32: ='PBSA Comparables'!E28 -> 352.5 | C32: ='PRS Benchmark'!C13 -> 495 | D32: ='Market Inputs'!B17 -> 1374 | E32: ='Market Inputs'!B18 -> 1919 | F32: =G15 -> 1314.0667 | G32: =E32/B32 -> 5.4439716 | H32: =E32/C32 -> 3.8767677 | I32: =E32/D32 -> 1.3966521
A33: Innsbruck | B33: ='PBSA Comparables'!E29 -> 374 | C33: ='PRS Benchmark'!D13 -> 473 | D33: ='Market Inputs'!C17 -> 520 | E33: ='Market Inputs'!C18 -> 700 | F33: =G20 -> 1199.8 | G33: =E33/B33 -> 1.8716578 | H33: =E33/C33 -> 1.4799154 | I33: =E33/D33 -> 1.3461538
A34: Passau | B34: ='PBSA Comparables'!E30 -> 325 | C34: ='PRS Benchmark'!E13 -> 225.5 | D34: ='Market Inputs'!D17 -> 350 | E34: ='Market Inputs'!D18 -> 550 | F34: =G25 -> 571.33333 | G34: =E34/B34 -> 1.6923077 | H34: =E34/C34 -> 2.4390244 | I34: =E34/D34 -> 1.5714286

Sheet Market Scorecard
A1: Market Attractiveness Scorecard — Multi-Factor Weighted Model
A2: Scores 1–10 per factor; weighted composite determines market ranking
A4: A. FACTOR WEIGHTS (User-Adjustable)
A5: Factor | B5: Weight | C5: Rationale
A6: University Prestige | B6: 0.1 | C6: Higher prestige = stronger demand from intl students willing to pay premium
A7: Total Student Population | B7: 0.12 | C7: Larger pool = deeper demand base
A8: International Student % | B8: 0.15 | C8: Intl students are core PBSA demand driver; higher willingness to pay
A9: Provision Rate (inverse) | B9: 0.15 | C9: Lower provision = more unmet demand = pricing power
A10: PRS Rent Level (€/sqm) | B10: 0.12 | C10: Higher PRS = larger absolute premium capture for PBSA
A11: City Income / GDP | B11: 0.08 | C11: Wealthier city = higher affordability ceiling
A12: PBSA Rent Growth (YoY) | B12: 0.08 | C12: Faster growth = momentum in market
A13: Occupancy Rate | B13: 0.1 | C13: Higher occupancy = demand exceeds supply
A14: Distance to University (avg) | B14: 0.05 | C14: Proximity premium for PBSA siting
A15: Demographic Diversity Index | B15: 0.05 | C15: More diverse origins = more PBSA-oriented demand
A16: Total Weight | B16: =SUM(B6:B15) -> 1
A18: B. RAW SCORES (1–10 Scale) & WEIGHTED COMPOSITE
A19: Factor | B19: Weight | C19: Munich Score | D19: Munich Wtd | E19: Innsbruck Score | F19: Innsbruck Wtd | G19: Passau Score | H19: Passau Wtd
A20: University Prestige | B20: =B6 -> 0.1 | C20: 10 | D20: =B20*C20 -> 1 | E20: 7 | F20: =B20*E20 -> 0.7 | G20: 5 | H20: =B20*G20 -> 0.5
A21: Total Student Population | B21: =B7 -> 0.12 | C21: 10 | D21: =B21*C21 -> 1.2 | E21: 6 | F21: =B21*E21 -> 0.72 | G21: 3 | H21: =B21*G21 -> 0.36
A22: International Student % | B22: =B8 -> 0.15 | C22: 8 | D22: =B22*C22 -> 1.2 | E22: 10 | F22: =B22*E22 -> 1.5 | G22: 5 | H22: =B22*G22 -> 0.75
A23: Provision Rate (inverse) | B23: =B9 -> 0.15 | C23: 7 | D23: =B23*C23 -> 1.05 | E23: 7 | F23: =B23*E23 -> 1.05 | G23: 8 | H23: =B23*G23 -> 1.2
A24: PRS Rent Level (€/sqm) | B24: =B10 -> 0.12 | C24: 10 | D24: =B24*C24 -> 1.2 | E24: 9 | F24: =B24*E24 -> 1.08 | G24: 4 | H24: =B24*G24 -> 0.48
A25: City Income / GDP | B25: =B11 -> 0.08 | C25: 10 | D25: =B25*C25 -> 0.8 | E25: 7 | F25: =B25*E25 -> 0.56 | G25: 5 | H25: =B25*G25 -> 0.4
A26: PBSA Rent Growth (YoY) | B26: =B12 -> 0.08 | C26: 8 | D26: =B26*C26 -> 0.64 | E26: 8 | F26: =B26*E26 -> 0.64 | G26: 6 | H26: =B26*G26 -> 0.48
A27: Occupancy Rate | B27: =B13 -> 0.1 | C27: 9 | D27: =B27*C27 -> 0.9 | E27: 8 | F27: =B27*E27 -> 0.8 | G27: 8 | H27: =B27*G27 -> 0.8
A28: Distance to University (avg) | B28: =B14 -> 0.05 | C28: 7 | D28: =B28*C28 -> 0.35 | E28: 8 | F28: =B28*E28 -> 0.4 | G28: 9 | H28: =B28*G28 -> 0.45
A29: Demographic Diversity Index | B29: =B15 -> 0.05 | C29: 8 | D29: =B29*C29 -> 0.4 | E29: 9 | F29: =B29*E29 -> 0.45 | G29: 5 | H29: =B29*G29 -> 0.25
A30: WEIGHTED COMPOSITE SCORE | D30: =SUM(D20:D29) -> 8.74 | F30: =SUM(F20:F29) -> 7.9 | H30: =SUM(H20:H29) -> 5.67
A31: RANK | D31: =IF(AND(D30>=F30,D30>=H30),1,IF(D30>=F30,2,3)) -> 1 | F31: =IF(AND(F30>=D30,F30>=H30),1,IF(F30>=D30,2,3)) -> 3 | H31: =IF(AND(H30>=D30,H30>=F30),1,IF(H30>=F30,2,3)) -> 3
A33: C. SCORE DERIVATION METHODOLOGY
A34: University Prestige: Based on QS/THE rankings. TUM (#28) + LMU (#59) = 10; UniIBK (#266) = 7; UniPassau (601-650) = 5
A35: Student Population: Munich 130k = 10; Innsbruck 35k = 6; Passau 10.6k = 3 (log-scaled)
A36: International %: Innsbruck 43.6% = 10; Munich 28.9% = 8; Passau 18.1% = 5
A37: Provision Rate (inverse): Lower = better. Passau ~11.4% = 8; Munich ~9.2% = 7; Innsbruck ~8.6% = 7
A38: PRS Rent: Munich €23/sqm = 10; Innsbruck €21 = 9; Passau €10 = 4
A39: Income/GDP: Munich €79k GDP/cap = 10; Innsbruck €55k = 7; Passau €35k = 5
A40: Distance to Uni: Passau compact campus = 9; Innsbruck concentrated = 8; Munich dispersed = 7
A41: Diversity Index: Innsbruck 50% intl from diverse origins = 9; Munich 29% but very diverse = 8; Passau 18% = 5

Sheet Sensitivity
A1: Sensitivity & Scenario Analysis
A3: A. ALL-IN RENT BY MULTIPLIER — Classic Studio (22 sqm)
A4: City | B4: PRS €/sqm | C4: 1.50x | D4: 1.80x | E4: 2.00x | F4: 2.29x | G4: 2.50x | H4: 2.80x | I4: 3.00x
A5: Munich | B5: 23 | C5: =B5*1.5*22 -> 759 | D5: =B5*1.8*22 -> 910.8 | E5: =B5*2*22 -> 1012 | F5: =B5*2.29*22 -> 1158.74 | G5: =B5*2.5*22 -> 1265 | H5: =B5*2.8*22 -> 1416.8 | I5: =B5*3*22 -> 1518
A6: Innsbruck | B6: 21 | C6: =B6*1.5*22 -> 693 | D6: =B6*1.8*22 -> 831.6 | E6: =B6*2*22 -> 924 | F6: =B6*2.29*22 -> 1057.98 | G6: =B6*2.5*22 -> 1155 | H6: =B6*2.8*22 -> 1293.6 | I6: =B6*3*22 -> 1386
A7: Passau | B7: 10 | C7: =B7*1.5*22 -> 330 | D7: =B7*1.8*22 -> 396 | E7: =B7*2*22 -> 440 | F7: =B7*2.29*22 -> 503.8 | G7: =B7*2.5*22 -> 550 | H7: =B7*2.8*22 -> 616 | I7: =B7*3*22 -> 660
A10: B. SCENARIO ANALYSIS — Premium PBSA Monthly Rent (Classic Studio 22sqm)
A11: Scenario | B11: Munich | C11: Innsbruck | D11: Passau | E11: Assumptions
A12: Conservative (1.5x PRS) | B12: =23*1.5*22 -> 759 | C12: =21*1.5*22 -> 693 | D12: =10*1.5*22 -> 330 | E12: Minimal premium; bare furnishing; limited amenities
A13: Base Case (2.0x PRS) | B13: =23*2*22 -> 1012 | C13: =21*2*22 -> 924 | D13: =10*2*22 -> 440 | E13: Standard PBSA; furnished; communal areas; utils included
A14: Munich Benchmark (2.29x PRS) | B14: =23*2.29*22 -> 1158.74 | C14: =21*2.29*22 -> 1057.98 | D14: =10*2.29*22 -> 503.8 | E14: Applies proven Munich premium ratio to local PRS
A15: Aggressive (2.8x PRS) | B15: =23*2.8*22 -> 1416.8 | C15: =21*2.8*22 -> 1293.6 | D15: =10*2.8*22 -> 616 | E15: Ultra-premium; THE FIZZ / Revo tier; full-service co-living
A16: Ultra-Premium (3.0x PRS) | B16: =23*3*22 -> 1518 | C16: =21*3*22 -> 1386 | D16: =10*3*22 -> 660 | E16: Top-of-market; concierge, gym, rooftop; luxury finishes
A19: C. AFFORDABILITY CHECK — PBSA Rent as % of Student Budget
A20: Metric | B20: Munich | C20: Innsbruck | D20: Passau
A21: Est. Monthly Student Budget | B21: 1200 | C21: 1000 | D21: 850
A22: Studentenwerk Rent / Budget | B22: =352/B21 -> 0.29333333 | C22: =374/C21 -> 0.374 | D22: =325/D21 -> 0.38235294
A23: Avg PBSA Rent / Budget | B23: =1374/B21 -> 1.145 | C23: =520/C21 -> 0.52 | D23: =350/D21 -> 0.41176471
A24: Premium PBSA (2.29x) / Budget | B24: =B14/B21 -> 0.96561667 | C24: =C14/C21 -> 1.05798 | D24: =D14/D21 -> 0.59270588
A25: Intl Student Budget (est. higher) | B25: 1600 | C25: 1300 | D25: 1100
A26: Premium PBSA / Intl Budget | B26: =B14/B25 -> 0.7242125 | C26: =C14/C25 -> 0.81383077 | D26: =D14/D25 -> 0.458
